{"status":"success","data":{"resultType":"vector","result":[{"metric":{"beta_kubernetes_io_arch":"amd64","beta_kubernetes_io_os":"linux","cpu":"total","id":"/kubelet.slice/kubelet-kubepods.slice/kubelet-kubepods-burstable.slice/kubelet-kubepods-burstable-poda4554c39_b73c_4fe7_a4a3_49f12fb29b96.slice","instance":"kind-worker2","job":"kubernetes-nodes-cadvisor","kubernetes_io_arch":"amd64","kubernetes_io_hostname":"kind-worker2","kubernetes_io_os":"linux","namespace":"default","pod":"app-gateway-istio-cb8df85c6-zsvnk"},"value":[1776235018.691,"0.07388496326093194"]}]}}